setup.py
tumbler/__init__.py
tumbler/cli.py
tumbler/core.py
tumbler/models.py
tumbler/testing.py
tumbler.egg-info/PKG-INFO
tumbler.egg-info/SOURCES.txt
tumbler.egg-info/dependency_links.txt
tumbler.egg-info/entry_points.txt
tumbler.egg-info/requires.txt
tumbler.egg-info/top_level.txt