Metadata-Version: 1.1
Name: tumbler
Version: 0.0.15
Summary: Tumbler is a simple layer that leverage flask with nice logs and automated settings management
Home-page: http://github.com/gabrielfalcao/tumbler
Author: Gabriel Falcao
Author-email: gabriel@nacaolivre.org
License: UNKNOWN
Platform: UNKNOWN
Classifier: License :: OSI Approved :: GNU General Public License v3 or later (GPLv3+)
